fractalcoef.py
imusim.py
quaternion.py
imusim-1.1.2.dist-info/LICENSE.md
imusim-1.1.2.dist-info/METADATA
imusim-1.1.2.dist-info/WHEEL
imusim-1.1.2.dist-info/top_level.txt
imusim-1.1.2.dist-info/RECORD
