Metadata-Version: 2.2
Name: imusim
Version: 1.1.2
Summary: IMU Simulator
Author-email: x-io Technologies Limited <info@x-io.co.uk>
License: 
Project-URL: Repository, https://github.com/xioTechnologies/IMU-Simulator
License-File: LICENSE.md
